dollar_lambda/__init__.py
dollar_lambda/args.py
dollar_lambda/data_structures.py
dollar_lambda/decorators.py
dollar_lambda/errors.py
dollar_lambda/parsers.py
dollar_lambda/py.typed
dollar_lambda/result.py
dollar_lambda-1.1.4.dist-info/LICENSE
dollar_lambda-1.1.4.dist-info/WHEEL
dollar_lambda-1.1.4.dist-info/METADATA
dollar_lambda-1.1.4.dist-info/RECORD
