Metadata-Version: 2.1
Name: dollar-lambda
Version: 1.1.4
Summary: An argument parser for Python built from functional first principles
Home-page: https://dollar-lambda.readthedocs.io
Keywords: argument-parser,parser,parser-combinators,functional-programming
Author: Ethan Brooks
Author-email: ethanabrooks@gmail.com
Maintainer: Ethan Brooks
Maintainer-email: ethanabrooks@gmail.com
Requires-Python: >=3.8,<4.0
Classifier: Development Status :: 3 - Alpha
Classifier: Intended Audience :: Developers
Classifier: License :: OSI Approved :: MIT License
Classifier: Programming Language :: Python :: 3
Classifier: Programming Language :: Python :: 3.10
Classifier: Programming Language :: Python :: 3.11
Classifier: Programming Language :: Python :: 3.8
Classifier: Programming Language :: Python :: 3.9
Classifier: Programming Language :: Python :: Implementation :: PyPy
Classifier: Topic :: Software Development :: Libraries :: Python Modules
Classifier: Topic :: Utilities
Requires-Dist: pytypeclass (>=0.1.1,<0.2.0)
Project-URL: Repository, https://github.com/ethanabrooks/dollar-lambda
